inspect_viz/__init__.py
inspect_viz/_version.py
inspect_viz/py.typed
inspect_viz/_core/__init__.py
inspect_viz/_core/_options.py
inspect_viz/_core/component.py
inspect_viz/_core/data.py
inspect_viz/_core/param.py
inspect_viz/_core/selection.py
inspect_viz/_core/types.py
inspect_viz/_util/__init__.py
inspect_viz/_util/_async.py
inspect_viz/_util/channels.py
inspect_viz/_util/color.py
inspect_viz/_util/constants.py
inspect_viz/_util/deprecation.py
inspect_viz/_util/inspect.py
inspect_viz/_util/instances.py
inspect_viz/_util/logger.py
inspect_viz/_util/marshall.py
inspect_viz/_util/notgiven.py
inspect_viz/_util/platform.py
inspect_viz/_util/stats.py
inspect_viz/_widgets/ag-grid.css
inspect_viz/_widgets/legend.css
inspect_viz/_widgets/mosaic.css
inspect_viz/_widgets/mosaic.js
inspect_viz/_widgets/nouislider.css
inspect_viz/_widgets/quarto.css
inspect_viz/_widgets/tomselect-bs5.css
inspect_viz/_widgets/tomselect-viz.css
inspect_viz/_widgets/tomselect.css
inspect_viz/_widgets/tooltips.css
inspect_viz/input/__init__.py
inspect_viz/input/_checkbox.py
inspect_viz/input/_checkbox_group.py
inspect_viz/input/_params.py
inspect_viz/input/_radio_group.py
inspect_viz/input/_search.py
inspect_viz/input/_select.py
inspect_viz/input/_slider.py
inspect_viz/input/_util.py
inspect_viz/interactor/__init__.py
inspect_viz/interactor/_brush.py
inspect_viz/interactor/_interactors.py
inspect_viz/layout/__init__.py
inspect_viz/layout/_concat.py
inspect_viz/layout/_space.py
inspect_viz/mark/__init__.py
inspect_viz/mark/_area.py
inspect_viz/mark/_arrow.py
inspect_viz/mark/_axis.py
inspect_viz/mark/_bar.py
inspect_viz/mark/_baseline.py
inspect_viz/mark/_cell.py
inspect_viz/mark/_channel.py
inspect_viz/mark/_contour.py
inspect_viz/mark/_delaunay.py
inspect_viz/mark/_dense.py
inspect_viz/mark/_density.py
inspect_viz/mark/_dot.py
inspect_viz/mark/_error_bar.py
inspect_viz/mark/_frame.py
inspect_viz/mark/_geo.py
inspect_viz/mark/_grid.py
inspect_viz/mark/_hexbin.py
inspect_viz/mark/_hexgrid.py
inspect_viz-0.3.5.dist-info/METADATA
inspect_viz-0.3.5.dist-info/WHEEL
inspect_viz-0.3.5.dist-info/licenses/LICENSE
inspect_viz-0.3.5.dist-info/RECORD
