Metadata-Version: 2.4
Name: inspect_viz
Version: 0.3.5
Summary: Data visualization for Inspect AI large language model evalutions.
Project-URL: Documentation, https://meridianlabs-ai.github.io/inspect_viz/
Project-URL: Source Code, https://github.com/meridianlabs-ai/inspect_viz
Project-URL: Issue Tracker, https://github.com/meridianlabs-ai/inspect_viz/issues
Author: Meridian Labs
License: MIT License
License-File: LICENSE
Requires-Python: >=3.10
Requires-Dist: anywidget>=0.9.0
Requires-Dist: ipython
Requires-Dist: narwhals>=1.15.1
Requires-Dist: nest-asyncio
Requires-Dist: pandas>=2.2.2
Requires-Dist: pillow
Requires-Dist: pyarrow>=15.0.0
Requires-Dist: pydantic
Requires-Dist: shortuuid
Requires-Dist: sniffio
Requires-Dist: traitlets>=5.9.0
Requires-Dist: typing-extensions>=4.9.0
Provides-Extra: dev
Requires-Dist: datamodel-code-generator; extra == 'dev'
Requires-Dist: jupyterlab; extra == 'dev'
Requires-Dist: mypy; extra == 'dev'
Requires-Dist: pandas-stubs; extra == 'dev'
Requires-Dist: playwright; extra == 'dev'
Requires-Dist: pyarrow-stubs; extra == 'dev'
Requires-Dist: pytest; extra == 'dev'
Requires-Dist: ruff; extra == 'dev'
Requires-Dist: types-pillow; extra == 'dev'
Requires-Dist: watchfiles; extra == 'dev'
Provides-Extra: doc
Requires-Dist: griffe; extra == 'doc'
Requires-Dist: jupyter; extra == 'doc'
Requires-Dist: markdown; extra == 'doc'
Requires-Dist: panflute; extra == 'doc'
Requires-Dist: pyyaml; extra == 'doc'
Requires-Dist: quarto-cli==1.7.31; extra == 'doc'
